git_util/__init__.py
git_util/cli.py
git_util/git_object.py
git_util/git_repo.py
git_util/git_util.py
git_util-0.1.1.dist-info/entry_points.txt
git_util-0.1.1.dist-info/WHEEL
git_util-0.1.1.dist-info/METADATA
git_util-0.1.1.dist-info/RECORD
